{
  "consumer": {
    "name": "Foo"
  },
  "provider": {
    "name": "Bar"
  },
  "interactions": [
    {
      "description": "a retrieve thing request",
      "request": {
        "method": "get",
        "path": "/thing",
        "query": "param=%5B%221%22%5D",
        "headers": {
          "Accept": "application/json"
        },
        "matchingRules": {
          "$.query.param": {
            "min": 1
          },
          "$.query.param[*].*": {
            "match": "type"
          }
        }
      },
      "response": {
        "status": 200,
        "headers": {
          "Content-Type": "application/json"
        },
        "body": {
          "company": "My big company",
          "factories": [
            {
              "location": "Sydney",
              "capacity": 5
            }
          ]
        },
        "matchingRules": {
          "$.body.company": {
            "match": "type"
          },
          "$.body.factories": {
            "min": 1
          },
          "$.body.factories[*].*": {
            "match": "type"
          }
        }
      }
    }
  ],
  "metadata": {
    "pactSpecification": {
      "version": "2.0.0"
    }
  }
}